<annotation>
    <folder>images</folder>
    <filename>ck5ijbbeyegb307705xnsd0sn.png</filename>
    <path>/output/images/ck5ijbbeyegb307705xnsd0sn.png</path>
    <source>
        <database>Unknown</database>
    </source>
    <size>
        <width>1440</width>
        <height>1080</height>
        <depth>3</depth>
    </size>
    <segmented>0</segmented>
    <object>
        <name>face</name>
        <pose>Unspecified</pose>
        <truncated>0</truncated>
        <difficult>0</difficult>
        <bndbox>
                <xmin>198</xmin>
                <ymin>61</ymin>
                <xmax>260</xmax>
                <ymax>146</ymax>
            </bndbox>
        </object>
    <object>
        <name>face</name>
        <pose>Unspecified</pose>
        <truncated>0</truncated>
        <difficult>0</difficult>
        <bndbox>
                <xmin>553</xmin>
                <ymin>51</ymin>
                <xmax>598</xmax>
                <ymax>110</ymax>
            </bndbox>
        </object>
    <object>
        <name>face</name>
        <pose>Unspecified</pose>
        <truncated>0</truncated>
        <difficult>0</difficult>
        <bndbox>
                <xmin>621</xmin>
                <ymin>88</ymin>
                <xmax>672</xmax>
                <ymax>144</ymax>
            </bndbox>
        </object>
    <object>
        <name>face</name>
        <pose>Unspecified</pose>
        <truncated>0</truncated>
        <difficult>0</difficult>
        <bndbox>
                <xmin>727</xmin>
                <ymin>77</ymin>
                <xmax>778</xmax>
                <ymax>138</ymax>
            </bndbox>
        </object>
    <object>
        <name>face</name>
        <pose>Unspecified</pose>
        <truncated>0</truncated>
        <difficult>0</difficult>
        <bndbox>
                <xmin>358</xmin>
                <ymin>38</ymin>
                <xmax>411</xmax>
                <ymax>93</ymax>
            </bndbox>
        </object>
    <object>
        <name>human</name>
        <pose>Unspecified</pose>
        <truncated>0</truncated>
        <difficult>0</difficult>
        <bndbox>
                <xmin>172</xmin>
                <ymin>62</ymin>
                <xmax>307</xmax>
                <ymax>442</ymax>
            </bndbox>
        </object>
    <object>
        <name>human</name>
        <pose>Unspecified</pose>
        <truncated>0</truncated>
        <difficult>0</difficult>
        <bndbox>
                <xmin>547</xmin>
                <ymin>37</ymin>
                <xmax>593</xmax>
                <ymax>347</ymax>
            </bndbox>
        </object>
    <object>
        <name>human</name>
        <pose>Unspecified</pose>
        <truncated>0</truncated>
        <difficult>0</difficult>
        <bndbox>
                <xmin>619</xmin>
                <ymin>92</ymin>
                <xmax>701</xmax>
                <ymax>355</ymax>
            </bndbox>
        </object>
    <object>
        <name>human</name>
        <pose>Unspecified</pose>
        <truncated>0</truncated>
        <difficult>0</difficult>
        <bndbox>
                <xmin>716</xmin>
                <ymin>79</ymin>
                <xmax>788</xmax>
                <ymax>348</ymax>
            </bndbox>
        </object>
    <object>
        <name>human</name>
        <pose>Unspecified</pose>
        <truncated>0</truncated>
        <difficult>0</difficult>
        <bndbox>
                <xmin>477</xmin>
                <ymin>56</ymin>
                <xmax>546</xmax>
                <ymax>341</ymax>
            </bndbox>
        </object>
    <object>
        <name>human</name>
        <pose>Unspecified</pose>
        <truncated>0</truncated>
        <difficult>0</difficult>
        <bndbox>
                <xmin>379</xmin>
                <ymin>635</ymin>
                <xmax>980</xmax>
                <ymax>1080</ymax>
            </bndbox>
        </object>
    <object>
        <name>human</name>
        <pose>Unspecified</pose>
        <truncated>0</truncated>
        <difficult>0</difficult>
        <bndbox>
                <xmin>346</xmin>
                <ymin>40</ymin>
                <xmax>425</xmax>
                <ymax>349</ymax>
            </bndbox>
        </object>
    </annotation>
